<annotation>
	<folder>เมล็ดดีติดกัน</folder>
	<filename>เเมล็ดดีติดกัน_(123).jpg</filename>
	<path>D:\year 5\coding project\CV vision\dataset\label\good\เมล็ดดีติดกัน\เเมล็ดดีติดกัน_(123).jpg</path>
	<source>
		<database>Unknown</database>
	</source>
	<size>
		<width>364</width>
		<height>294</height>
		<depth>3</depth>
	</size>
	<segmented>0</segmented>
	<object>
		<name>เมล็ดดีติดกัน</name>
		<pose>Unspecified</pose>
		<truncated>0</truncated>
		<difficult>0</difficult>
		<bndbox>
			<xmin>58</xmin>
			<ymin>73</ymin>
			<xmax>285</xmax>
			<ymax>198</ymax>
		</bndbox>
	</object>
</annotation>
